aionefit/__init__.py
aionefit/provider/__init__.py
aionefit/provider/pyaes_impl.py
aionefit/provider/slixmpp_impl.py
aionefit_updated-0.16.dist-info/METADATA
aionefit_updated-0.16.dist-info/WHEEL
aionefit_updated-0.16.dist-info/top_level.txt
aionefit_updated-0.16.dist-info/RECORD
