Metadata-Version: 2.4
Name: aionefit_updated
Version: 0.16
Summary: asyncio library for Bosch thermostats
Home-page: https://github.com/spoetnik/aionefit
Author: Martijn de Geus
Author-email: m.degeus@nise.nl
License: MIT
Classifier: Programming Language :: Python
Classifier: Programming Language :: Python :: 3
Classifier: Programming Language :: Python :: 3.9
Classifier: Programming Language :: Python :: Implementation :: CPython
Classifier: Programming Language :: Python :: Implementation :: PyPy
Requires-Python: >=3.9.0
Requires-Dist: pyaes
Requires-Dist: slixmpp==1.11.0
Dynamic: author
Dynamic: author-email
Dynamic: classifier
Dynamic: description
Dynamic: description-content-type
Dynamic: home-page
Dynamic: license
Dynamic: requires-dist
Dynamic: requires-python
Dynamic: summary
